LICENSE
README.md
setup.cfg
setup.py
ocpapi/__init__.py
ocpapi/version.py
ocpapi.egg-info/PKG-INFO
ocpapi.egg-info/SOURCES.txt
ocpapi.egg-info/dependency_links.txt
ocpapi.egg-info/requires.txt
ocpapi.egg-info/top_level.txt
ocpapi/client/__init__.py
ocpapi/client/client.py
ocpapi/client/models.py
ocpapi/client/ui.py
ocpapi/workflows/__init__.py
ocpapi/workflows/adsorbates.py
ocpapi/workflows/context.py
ocpapi/workflows/filter.py
ocpapi/workflows/log.py
ocpapi/workflows/retry.py