Metadata-Version: 2.1
Name: ocpapi
Version: 1.0.0
Summary: Python client library for the Open Catalyst API
Author: Open Catalyst Project
Author-email: opencatalyst@meta.com
Classifier: Programming Language :: Python :: 3
Classifier: License :: OSI Approved :: MIT License
Classifier: Operating System :: OS Independent
Requires-Python: >=3.9
Provides-Extra: dev
License-File: LICENSE
